psqlgml/__init__.py
psqlgml/cli.py
psqlgml/py.typed
psqlgml/resources.py
psqlgml/schema.py
psqlgml/types.py
psqlgml/typings.py
psqlgml/validators.py
psqlgml/visualization.py
psqlgml/dictionaries/__init__.py
psqlgml/dictionaries/readers.py
psqlgml/dictionaries/repository.py
psqlgml/dictionaries/schemas.py
psqlgml/templates/schema.jinja2
psqlgml-0.2.4.dist-info/LICENSE
psqlgml-0.2.4.dist-info/METADATA
psqlgml-0.2.4.dist-info/WHEEL
psqlgml-0.2.4.dist-info/entry_points.txt
psqlgml-0.2.4.dist-info/top_level.txt
psqlgml-0.2.4.dist-info/zip-safe
psqlgml-0.2.4.dist-info/RECORD
