Metadata-Version: 2.1
Name: psqlgml
Version: 0.2.4
Home-page: https://github.com/kulgan/psqlgml
Author: Rowland Ogwara
Author-email: r.ogwara@gmail.com
License: Apache Software License 2.0
Keywords: gdcdictionary,psqlgraph,graphml,mocks,testing
Classifier: Development Status :: 4 - Beta
Classifier: Intended Audience :: Developers
Classifier: License :: OSI Approved :: Apache Software License
Classifier: Programming Language :: Python :: 3 :: Only
Classifier: Programming Language :: Python :: 3.6
Classifier: Programming Language :: Python :: 3.7
Classifier: Programming Language :: Python :: 3.8
Classifier: Programming Language :: Python :: 3.9
Classifier: Programming Language :: Python :: 3.10
Classifier: Topic :: Database
Requires-Python: >=3.6
License-File: LICENSE
Requires-Dist: attrs
Requires-Dist: click
Requires-Dist: colored
Requires-Dist: dulwich (>=0.20.31)
Requires-Dist: graphviz
Requires-Dist: Jinja2
Requires-Dist: jsonschema
Requires-Dist: PyYaml
Requires-Dist: typing-extensions ; python_version < "3.8"
Provides-Extra: changelog
Requires-Dist: towncrier ; extra == 'changelog'
Provides-Extra: dev
Requires-Dist: coverage[toml] ; extra == 'dev'
Requires-Dist: pillow ; extra == 'dev'
Requires-Dist: pre-commit ; extra == 'dev'
Requires-Dist: pytest ; extra == 'dev'
Requires-Dist: pytest-cov ; extra == 'dev'
Provides-Extra: docs
Requires-Dist: sphinx ; extra == 'docs'
Requires-Dist: sphinx-rtd-theme ; extra == 'docs'
Requires-Dist: sphinxcontrib-napoleon ; extra == 'docs'
